doc2image/__init__.py
doc2image/pdf2img.py
doc_parse/__init__.py
doc_parse/pdf_parse.py
layout/__init__.py
utils/__init__.py
utils/util.py
docminer-0.0.1.dist-info/LICENSE
docminer-0.0.1.dist-info/METADATA
docminer-0.0.1.dist-info/WHEEL
docminer-0.0.1.dist-info/top_level.txt
docminer-0.0.1.dist-info/RECORD
